pyKeksik/__init__.py
pyKeksik/api.py
pyKeksik-1.2.dist-info/METADATA
pyKeksik-1.2.dist-info/WHEEL
pyKeksik-1.2.dist-info/top_level.txt
pyKeksik-1.2.dist-info/RECORD
