Metadata-Version: 2.1
Name: pyKeksik
Version: 1.2
Summary: Неофициальная библиотека для работы с API https://keksik.io
Home-page: https://github.com/Friendosie/pyKeksik
Author: Friendosie
Author-email: friendosie@gmail.com
License: MIT
Requires-Dist: requests
